assi/__init__.py
assi/cli.py
assi/cookiecutter.py
assi/datastorage.py
assi/graphics.py
assi/modelstorage.py
assi/bin/__init__.py
assi/bin/record.py
assi/bin/scope.py
assi/clearml/__init__.py
assi/clearml/datastorage.py
assi/clearml/modelstorage.py
assi/clearml/utils.py
assi/datasets/__init__.py
assi/datasets/dataset_segmented.py
assi/datasets/dcase2025t2/download.py
assi/datasets/dcase2025t2/storage.py
assi/datasets/mimii/download.py
assi/datasets/mimii/storage.py
assi/io/__init__.py
assi/io/basis.py
assi/io/filter.py
assi/io/frame.py
assi/io/section.py
assi/io/stream.py
assi/io/util.py
assi/io/window.py
assi/models/__init__.py
assi/models/autoencoder/__init__.py
assi/models/autoencoder/module.py
assi/models/autoencoder/module_fit_config.yml
assi/models/mae/__init__.py
assi/models/mae/module.py
assi/models/mae/module_fit_config.yml
assi/models/mcnmf/example_mcnmf.ipynb
assi/models/mcnmf/gauss_mcnmf.py
assi/models/mcnmf/mcnmf.md
assi/models/nflows/__init__.py
assi/models/nflows/module.py
assi/models/nflows/module_fit_config.yml
assi/ngui/__init__.py
assi/ngui/pre.py
assi/nodes/__init__.py
assi/nodes/node.py
assi/nodes/pool.py
assi/nodes/pydantic.py
assi/nodes/utils.py
assi/nodes_app/__init__.py
assi/nodes_app/configurable.py
assi/nodes_app/pool_service.py
assi/nodes_app/utils.py
assi/postprocessing/__init__.py
assi/postprocessing/results_segmented.py
assi/postprocessing/metrics/unsupervised.py
assi/postprocessing/results_apps/dev_unsupervised_results.py
assi/postprocessing/results_apps/unsupervised_results.py
assi/postprocessing/results_apps/web/dist/unsupervised_results.js
assi/postprocessing/results_apps/web/dist/.vite/manifest.json
assi/postprocessing/results_apps/web/dist/assets/unsupervised_results-BWkxq66O.css
assi/postprocessing/results_apps/web/templates/index.jinja2
assi/scope/__init__.py
assi/scope/beamformer.py
assi/scope/log.py
assi/scope/main.py
assi/scope/mode.py
assi/scope/source.py
pyassi-0.0.1.dist-info/METADATA
pyassi-0.0.1.dist-info/WHEEL
pyassi-0.0.1.dist-info/entry_points.txt
pyassi-0.0.1.dist-info/licenses/LICENSE
pyassi-0.0.1.dist-info/RECORD
